matter_server/__init__.py
matter_server/py.typed
matter_server/client/__init__.py
matter_server/client/client.py
matter_server/client/connection.py
matter_server/client/exceptions.py
matter_server/client/models/__init__.py
matter_server/client/models/device_types.py
matter_server/client/models/node.py
matter_server/common/__init__.py
matter_server/common/const.py
matter_server/common/custom_clusters.py
matter_server/common/errors.py
matter_server/common/models.py
matter_server/common/helpers/api.py
matter_server/common/helpers/json.py
matter_server/common/helpers/logger.py
matter_server/common/helpers/util.py
matter_server/dashboard/index.html
matter_server/dashboard/js/commission-node-dialog-DmwXWFIF.js
matter_server/dashboard/js/commission-node-existing-Cq7mUp9G.js
matter_server/dashboard/js/commission-node-thread-BDrL48jo.js
matter_server/dashboard/js/commission-node-wifi-D5vtTBoN.js
matter_server/dashboard/js/dialog-box-CX2c43pz.js
matter_server/dashboard/js/fire_event-3RWMUKjQ.js
matter_server/dashboard/js/main.js
matter_server/dashboard/js/matter-dashboard-app-BG9E_Nxv.js
matter_server/dashboard/js/node-binding-dialog-CcYm8slT.js
matter_server/dashboard/js/outlined-text-field-DMC3zyTK.js
matter_server/dashboard/js/prevent_default--7eNqPmY.js
matter_server/server/__init__.py
matter_server/server/__main__.py
matter_server/server/client_handler.py
matter_server/server/const.py
matter_server/server/device_controller.py
matter_server/server/sdk.py
matter_server/server/server.py
matter_server/server/stack.py
matter_server/server/storage.py
matter_server/server/vendor_info.py
matter_server/server/helpers/__init__.py
matter_server/server/helpers/attributes.py
matter_server/server/helpers/custom_web_runner.py
matter_server/server/helpers/paa_certificates.py
matter_server/server/helpers/utils.py
matter_server/server/ota/__init__.py
matter_server/server/ota/dcl.py
matter_server/server/ota/provider.py
python_matter_server-8.1.2.dist-info/licenses/LICENSE
python_matter_server-8.1.2.dist-info/METADATA
python_matter_server-8.1.2.dist-info/WHEEL
python_matter_server-8.1.2.dist-info/entry_points.txt
python_matter_server-8.1.2.dist-info/top_level.txt
python_matter_server-8.1.2.dist-info/RECORD
