Metadata-Version: 2.4
Name: python-matter-server
Version: 8.1.2
Summary: Open Home Foundation Matter Server
Author-email: The Home Assistant Authors <hello@home-assistant.io>
License: Apache-2.0
Platform: any
Classifier: Development Status :: 5 - Production/Stable
Classifier: Intended Audience :: Developers
Classifier: Environment :: Console
Classifier: Programming Language :: Python :: 3.12
Classifier: Programming Language :: Python :: 3.13
Classifier: Topic :: Home Automation
Requires-Python: >=3.12
License-File: LICENSE
Requires-Dist: aiohttp
Requires-Dist: aiorun
Requires-Dist: coloredlogs
Requires-Dist: orjson
Requires-Dist: home-assistant-chip-clusters==2025.7.0
Provides-Extra: server
Requires-Dist: aiohttp==3.13.2; extra == "server"
Requires-Dist: aiorun==2025.1.1; extra == "server"
Requires-Dist: atomicwrites==1.4.1; extra == "server"
Requires-Dist: coloredlogs==15.0.1; extra == "server"
Requires-Dist: cryptography==46.0.3; extra == "server"
Requires-Dist: orjson==3.11.5; extra == "server"
Requires-Dist: zeroconf==0.148.0; extra == "server"
Requires-Dist: home-assistant-chip-core==2025.7.0; extra == "server"
Provides-Extra: test
Requires-Dist: aioresponses==0.7.8; extra == "test"
Requires-Dist: codespell==2.4.1; extra == "test"
Requires-Dist: isort==7.0.0; extra == "test"
Requires-Dist: mypy==1.19.1; extra == "test"
Requires-Dist: pre-commit==4.5.0; extra == "test"
Requires-Dist: pre-commit-hooks==6.0.0; extra == "test"
Requires-Dist: pylint==4.0.4; extra == "test"
Requires-Dist: pytest==9.0.2; extra == "test"
Requires-Dist: pytest-asyncio==1.3.0; extra == "test"
Requires-Dist: pytest-aiohttp==1.1.0; extra == "test"
Requires-Dist: pytest-cov==7.0.0; extra == "test"
Requires-Dist: ruff==0.14.9; extra == "test"
Requires-Dist: tomli==2.3.0; extra == "test"
Dynamic: license-file
